{"lessonId":"HF-102-01","moduleId":"HF-102","courseId":"HF","title":"Understanding Fatigue","type":"lesson","content":"Fatigue is a physiological state of reduced mental and physical capability. It results from sleep loss, time awake, circadian disruption, and sustained effort. Fatigued people have impaired judgment, slower reactions, increased errors, and—critically—poor awareness of their impairment.","mcq":{"question":"A person who has been awake for 24 hours has impairment roughly equivalent to what blood alcohol level?","options":{"A":"No equivalent—fatigue is different","B":"0.05-0.10% BAC","C":"0.01% BAC","D":"Fatigue doesn't impair like alcohol"},"correctOption":"B","explanation":"Research shows 24-hour wakefulness produces impairment similar to legal intoxication. We accept that drunk operation is unsafe but often treat fatigue as a personal choice. Both impair safety-critical performance."},"openQuestions":["How do you know when you're too fatigued to perform safely?","Does your organization treat fatigue as a safety issue?"]}
